mcp_maya_small_tools/__init__.py
mcp_maya_small_tools/main.py
mcp_maya_small_tools/server.py
mcp_maya_small_tools-0.1.5.dist-info/METADATA
mcp_maya_small_tools-0.1.5.dist-info/WHEEL
mcp_maya_small_tools-0.1.5.dist-info/entry_points.txt
mcp_maya_small_tools-0.1.5.dist-info/top_level.txt
mcp_maya_small_tools-0.1.5.dist-info/RECORD
