Metadata-Version: 2.4
Name: mcp-maya-small-tools
Version: 0.1.5
Summary: Add your description here
Requires-Python: >=3.10
Requires-Dist: mcp[cli]>=1.21.1
